__init__.py
cuda/euler_update_Interface.cpp
cuda/euler_update_Kernel.cu
cuda/fluxCal_1stOrder_Interface.cpp
cuda/fluxCal_1stOrder_Kernel.cu
cuda/fluxCal_2ndOrder_Interface.cpp
cuda/fluxCal_2ndOrder_Kernel.cu
cuda/fluxMask_Interface.cpp
cuda/fluxMask_Kernel.cu
cuda/frictionImplicit_andUpdate_Interface.cpp
cuda/frictionImplicit_andUpdate_Kernel.cu
cuda/gpu.cuh
cuda/infiltration_sewer_Interface.cpp
cuda/infiltration_sewer_Kernel.cu
cuda/setup.py
cuda/stationPrecipitation_Interface.cpp
cuda/stationPrecipitation_Kernel.cu
cuda/timeControl_Interface.cpp
cuda/timeControl_Kernel.cu
hipims/InputHipims.py
hipims/SWE.py
hipims/__init__.py
hipims/banner.txt
hipims/euler_update.so
hipims/flood.py
hipims/fluxCal_1stOrder.so
hipims/fluxCal_2ndOrder.so
hipims/fluxMask.so
hipims/frictionImplicit_andUpdate.so
hipims/get_sample.py
hipims/infiltration_sewer.so
hipims/postProcessing.py
hipims/preProcessing.py
hipims/stationPrecipitation.so
hipims/timeControl.so
hipims/toolkit.py
hipims/visualization.py
hipims2-0.0.0.0.dist-info/LICENCE
hipims2-0.0.0.0.dist-info/METADATA
hipims2-0.0.0.0.dist-info/WHEEL
hipims2-0.0.0.0.dist-info/top_level.txt
hipims2-0.0.0.0.dist-info/RECORD
